tisthemachinelearner/__init__.py
tisthemachinelearner/base.py
tisthemachinelearner/classifier.py
tisthemachinelearner/finitedifftrainer.py
tisthemachinelearner/regressor.py
tisthemachinelearner/wrappedcalibratedclassifier.py
tisthemachinelearner-0.8.4.dist-info/METADATA
tisthemachinelearner-0.8.4.dist-info/WHEEL
tisthemachinelearner-0.8.4.dist-info/licenses/LICENSE
tisthemachinelearner-0.8.4.dist-info/RECORD
