Metadata-Version: 2.4
Name: tisthemachinelearner
Version: 0.8.4
Summary: Lightweight interface to scikit-learn, xgboost, lightgbm, catboost, with 2 classes
License-File: LICENSE
Requires-Python: >=3.8
Requires-Dist: nnetsauce
Requires-Dist: unifiedbooster
